yta_ai_utils/__init__.py
yta_ai_utils/blip.py
yta_ai_utils/experimental/__init__.py
yta_ai_utils/experimental/chat_assistant/__init__.py
yta_ai_utils/experimental/chat_assistant/ai21.py
yta_ai_utils/experimental/chat_assistant/chat_gpt.py
yta_ai_utils/experimental/chat_assistant/prompts.py
yta_ai_utils/experimental/generation/__init__.py
yta_ai_utils/experimental/generation/image/__init__.py
yta_ai_utils/experimental/generation/image/aifumes.py
yta_ai_utils/experimental/generation/music/__init__.py
yta_ai_utils/experimental/generation/music/tuna_voicemod.py
yta_ai_utils/experimental/narration_script_generator.py
yta_ai_utils/experimental/song_lyrics.py
yta_ai_utils/experimental/transcription.py
yta_ai_utils/flux.py
yta_ai_utils/gemini.py
yta_ai_utils/hugginface.py
yta_ai_utils/leonardo.py
yta_ai_utils/llava.py
yta_ai_utils/openai.py
yta_ai_utils/pollinations.py
yta_ai_utils/prodia.py
yta_ai_utils/prompts/__init__.py
yta_ai_utils/prompts/religious.py
yta_ai_utils-0.0.12.dist-info/LICENSE
yta_ai_utils-0.0.12.dist-info/METADATA
yta_ai_utils-0.0.12.dist-info/WHEEL
yta_ai_utils-0.0.12.dist-info/RECORD
