Metadata-Version: 2.3
Name: yta-ai-utils
Version: 0.0.12
Summary: Youtube Autónomo AI utils are here.
Author: danialcala94
Author-email: danielalcalavalera@gmail.com
Requires-Python: ==3.9
Classifier: Programming Language :: Python :: 3
Classifier: Programming Language :: Python :: 3.9
Requires-Dist: ai21 (>=2.1.2,<3.0.0)
Requires-Dist: google-generativeai (>=0.6.0,<1.0.0)
Requires-Dist: ollama (>=0.3.1,<1.0.0)
Requires-Dist: openai (>=1.3.8,<2.0.0)
Requires-Dist: python-dotenv (>=1.0.0,<2.0.0)
Requires-Dist: re_gpt (>=3.0.1,<4.0.0)
Requires-Dist: requests (>=2.32.3,<3.0.0)
Requires-Dist: tqdm (>=4.66.1,<5.0.0)
Requires-Dist: transformers (>=4.0.0,<5.0.0)
Requires-Dist: whisper_timestamped (>=1.14.2,<2.0.0)
Requires-Dist: yta_general_utils (>=0.0.250,<0.1.0)
